ib_mcp/__init__.py
ib_mcp/server.py
ib_mcp-0.2.9.dist-info/LICENSE
ib_mcp-0.2.9.dist-info/METADATA
ib_mcp-0.2.9.dist-info/WHEEL
ib_mcp-0.2.9.dist-info/entry_points.txt
ib_mcp-0.2.9.dist-info/RECORD
