Metadata-Version: 2.1
Name: ib-mcp
Version: 0.2.9
Summary: Model Context Protocol (MCP) server exposing Interactive Brokers data via ib_async + FastMCP
Home-page: https://github.com/Hellek1/ib-mcp
License: BSD-3-Clause
Keywords: interactive-brokers,ib,ibapi,tws,asyncio,mcp,fastmcp,llm
Author: David Hellekalek
Author-email: hellekalek@gmail.com
Requires-Python: >=3.12,<4.0
Classifier: Development Status :: 4 - Beta
Classifier: Intended Audience :: Developers
Classifier: License :: OSI Approved :: BSD License
Classifier: Programming Language :: Python :: 3
Classifier: Programming Language :: Python :: 3.12
Classifier: Programming Language :: Python :: 3 :: Only
Classifier: Programming Language :: Python :: 3.13
Classifier: Topic :: Office/Business :: Financial :: Investment
Classifier: Typing :: Typed
Requires-Dist: authlib (>=1.6.4)
Requires-Dist: defusedxml (>=0.7.1)
Requires-Dist: fastmcp (>=2.11.0)
Requires-Dist: ib_async (>=2.0.1,<3.0.0)
Requires-Dist: tzdata (>=2024.1)
Project-URL: Documentation, https://github.com/Hellek1/ib-mcp#readme
Project-URL: Repository, https://github.com/Hellek1/ib-mcp
